nanow/_init__.py
nanow/cli.py
nano_wakatime-1.0.0.dist-info/METADATA
nano_wakatime-1.0.0.dist-info/WHEEL
nano_wakatime-1.0.0.dist-info/entry_points.txt
nano_wakatime-1.0.0.dist-info/top_level.txt
nano_wakatime-1.0.0.dist-info/RECORD
