Metadata-Version: 2.4
Name: nano-wakatime
Version: 1.0.0
Summary: A WakaTime plugin wrapper for GNU Nano
Author-email: Alan Nato <alanwnato@gmail.com>
License: MIT
Project-URL: Homepage, https://github.com/iamnotnato/nano-wakatime
Requires-Python: >=3.7
Requires-Dist: watchdog>=2.1.0
